uctopic/__init__.py
uctopic/dataloader.py
uctopic/kmeans.py
uctopic/models.py
uctopic/tokenizer.py
uctopic/tool.py
uctopic/trainer.py
uctopic/utils.py
uctopic-0.3.dist-info/LICENSE
uctopic-0.3.dist-info/METADATA
uctopic-0.3.dist-info/WHEEL
uctopic-0.3.dist-info/top_level.txt
uctopic-0.3.dist-info/RECORD
